{
 "shops": {
  "GameStop US": {
   "Pitch Black (ME05)": "irraggiungibile",
   "30th Celebration": "irraggiungibile",
   "Storm Emerald (ME06)": "irraggiungibile",
   "Chaos Rising (ME04)": "irraggiungibile",
   "Phantasmal Flames (ME02)": "irraggiungibile",
   "Pokémon 151": "irraggiungibile",
   "Prismatic Evolutions": "irraggiungibile",
   "Crown Zenith": "irraggiungibile",
   "Destined Rivals": "irraggiungibile"
  },
  "Amazon.it": {
   "Pitch Black (ME05)": "non listato",
   "30th Celebration": "non listato",
   "Storm Emerald (ME06)": "non listato",
   "Chaos Rising (ME04)": "non listato",
   "Phantasmal Flames (ME02)": "non listato",
   "Pokémon 151": "non listato",
   "Prismatic Evolutions": "non listato",
   "Crown Zenith": "non listato",
   "Destined Rivals": "non listato"
  },
  "Cardmarket": {
   "Pitch Black (ME05)": "irraggiungibile",
   "30th Celebration": "irraggiungibile",
   "Storm Emerald (ME06)": "irraggiungibile",
   "Chaos Rising (ME04)": "irraggiungibile",
   "Phantasmal Flames (ME02)": "irraggiungibile",
   "Pokémon 151": "irraggiungibile",
   "Prismatic Evolutions": "irraggiungibile",
   "Crown Zenith": "irraggiungibile",
   "Destined Rivals": "irraggiungibile"
  },
  "Pokemon Center": {
   "Pitch Black (ME05)": "irraggiungibile",
   "30th Celebration": "irraggiungibile",
   "Storm Emerald (ME06)": "irraggiungibile",
   "Chaos Rising (ME04)": "irraggiungibile",
   "Phantasmal Flames (ME02)": "irraggiungibile",
   "Pokémon 151": "non listato",
   "Prismatic Evolutions": "non listato",
   "Crown Zenith": "non listato",
   "Destined Rivals": "non listato"
  },
  "TCGplayer": {
   "Pitch Black (ME05)": "non listato",
   "30th Celebration": "non listato",
   "Storm Emerald (ME06)": "non listato",
   "Chaos Rising (ME04)": "non listato",
   "Phantasmal Flames (ME02)": "non listato",
   "Pokémon 151": "non listato",
   "Prismatic Evolutions": "non listato",
   "Crown Zenith": "non listato",
   "Destined Rivals": "non listato"
  },
  "SunnyStore": {
   "Pitch Black (ME05)": "listato",
   "30th Celebration": "esaurito",
   "Storm Emerald (ME06)": "listato",
   "Chaos Rising (ME04)": "esaurito",
   "Phantasmal Flames (ME02)": "esaurito",
   "Pokémon 151": "disponibile",
   "Prismatic Evolutions": "esaurito",
   "Crown Zenith": "listato",
   "Destined Rivals": "esaurito"
  },
  "Poke-Power": {
   "Pitch Black (ME05)": "listato",
   "30th Celebration": "listato",
   "Storm Emerald (ME06)": "listato",
   "Chaos Rising (ME04)": "listato",
   "Phantasmal Flames (ME02)": "listato",
   "Pokémon 151": "listato",
   "Prismatic Evolutions": "listato",
   "Crown Zenith": "listato",
   "Destined Rivals": "listato"
  },
  "Rogerz": {
   "Pitch Black (ME05)": "listato",
   "30th Celebration": "listato",
   "Storm Emerald (ME06)": "listato",
   "Chaos Rising (ME04)": "listato",
   "Phantasmal Flames (ME02)": "listato",
   "Pokémon 151": "listato",
   "Prismatic Evolutions": "listato",
   "Crown Zenith": "listato",
   "Destined Rivals": "listato"
  },
  "EuroTCG": {
   "Pitch Black (ME05)": "listato",
   "30th Celebration": "listato",
   "Storm Emerald (ME06)": "listato",
   "Chaos Rising (ME04)": "esaurito",
   "Phantasmal Flames (ME02)": "esaurito",
   "Pokémon 151": "listato",
   "Prismatic Evolutions": "listato",
   "Crown Zenith": "listato",
   "Destined Rivals": "esaurito"
  },
  "eFantasy": {
   "Pitch Black (ME05)": "non listato",
   "30th Celebration": "non listato",
   "Storm Emerald (ME06)": "non listato",
   "Chaos Rising (ME04)": "non listato",
   "Phantasmal Flames (ME02)": "non listato",
   "Pokémon 151": "non listato",
   "Prismatic Evolutions": "non listato",
   "Crown Zenith": "non listato",
   "Destined Rivals": "non listato"
  },
  "Blackfire": {
   "Pitch Black (ME05)": "non listato",
   "30th Celebration": "non listato",
   "Storm Emerald (ME06)": "non listato",
   "Chaos Rising (ME04)": "non listato",
   "Phantasmal Flames (ME02)": "non listato",
   "Pokémon 151": "non listato",
   "Prismatic Evolutions": "non listato",
   "Crown Zenith": "non listato",
   "Destined Rivals": "non listato"
  },
  "AllDayTCG": {
   "Pitch Black (ME05)": "listato",
   "30th Celebration": "listato",
   "Storm Emerald (ME06)": "listato",
   "Chaos Rising (ME04)": "listato",
   "Phantasmal Flames (ME02)": "esaurito",
   "Pokémon 151": "esaurito",
   "Prismatic Evolutions": "esaurito",
   "Crown Zenith": "irraggiungibile",
   "Destined Rivals": "irraggiungibile"
  },
  "CardZone": {
   "Pitch Black (ME05)": "disponibile",
   "30th Celebration": "disponibile",
   "Storm Emerald (ME06)": "disponibile",
   "Chaos Rising (ME04)": "listato",
   "Phantasmal Flames (ME02)": "disponibile",
   "Pokémon 151": "esaurito",
   "Prismatic Evolutions": "esaurito",
   "Crown Zenith": "disponibile",
   "Destined Rivals": "irraggiungibile"
  },
  "God of Cards": {
   "Pitch Black (ME05)": "listato",
   "30th Celebration": "listato",
   "Storm Emerald (ME06)": "listato",
   "Chaos Rising (ME04)": "listato",
   "Phantasmal Flames (ME02)": "listato",
   "Pokémon 151": "disponibile",
   "Prismatic Evolutions": "disponibile",
   "Crown Zenith": "irraggiungibile",
   "Destined Rivals": "irraggiungibile"
  },
  "Pokeseller14": {
   "Pitch Black (ME05)": "irraggiungibile",
   "30th Celebration": "irraggiungibile",
   "Storm Emerald (ME06)": "irraggiungibile",
   "Chaos Rising (ME04)": "irraggiungibile",
   "Phantasmal Flames (ME02)": "irraggiungibile",
   "Pokémon 151": "irraggiungibile",
   "Prismatic Evolutions": "irraggiungibile",
   "Crown Zenith": "irraggiungibile",
   "Destined Rivals": "irraggiungibile"
  },
  "OutpostBrussels": {
   "Pitch Black (ME05)": "esaurito",
   "30th Celebration": "listato",
   "Storm Emerald (ME06)": "listato",
   "Chaos Rising (ME04)": "esaurito",
   "Phantasmal Flames (ME02)": "esaurito",
   "Pokémon 151": "esaurito",
   "Prismatic Evolutions": "esaurito",
   "Crown Zenith": "esaurito",
   "Destined Rivals": "esaurito"
  },
  "Total Cards (UK)": {
   "Pitch Black (ME05)": "listato",
   "30th Celebration": "listato",
   "Storm Emerald (ME06)": "listato",
   "Chaos Rising (ME04)": "listato",
   "Phantasmal Flames (ME02)": "listato",
   "Pokémon 151": "irraggiungibile",
   "Prismatic Evolutions": "irraggiungibile",
   "Crown Zenith": "irraggiungibile",
   "Destined Rivals": "irraggiungibile"
  },
  "Kerailykortti": {
   "Pitch Black (ME05)": "listato",
   "30th Celebration": "listato",
   "Storm Emerald (ME06)": "listato",
   "Chaos Rising (ME04)": "listato",
   "Phantasmal Flames (ME02)": "listato",
   "Pokémon 151": "non listato",
   "Prismatic Evolutions": "listato",
   "Crown Zenith": "listato",
   "Destined Rivals": "listato"
  },
  "Chaos Cards (UK)": {
   "Pitch Black (ME05)": "non listato",
   "30th Celebration": "non listato",
   "Storm Emerald (ME06)": "non listato",
   "Chaos Rising (ME04)": "non listato",
   "Phantasmal Flames (ME02)": "non listato",
   "Pokémon 151": "non listato",
   "Prismatic Evolutions": "non listato",
   "Crown Zenith": "non listato",
   "Destined Rivals": "non listato"
  },
  "Wayland Games (UK)": {
   "Pitch Black (ME05)": "irraggiungibile",
   "30th Celebration": "irraggiungibile",
   "Storm Emerald (ME06)": "irraggiungibile",
   "Chaos Rising (ME04)": "irraggiungibile",
   "Phantasmal Flames (ME02)": "irraggiungibile",
   "Pokémon 151": "irraggiungibile",
   "Prismatic Evolutions": "irraggiungibile",
   "Crown Zenith": "irraggiungibile",
   "Destined Rivals": "irraggiungibile"
  },
  "Packratt (UK)": {
   "Pitch Black (ME05)": "listato",
   "30th Celebration": "listato",
   "Storm Emerald (ME06)": "listato",
   "Chaos Rising (ME04)": "disponibile",
   "Phantasmal Flames (ME02)": "esaurito",
   "Pokémon 151": "disponibile",
   "Prismatic Evolutions": "listato",
   "Crown Zenith": "listato",
   "Destined Rivals": "esaurito"
  },
  "CrispyCards": {
   "Pitch Black (ME05)": "listato",
   "30th Celebration": "listato",
   "Storm Emerald (ME06)": "listato",
   "Chaos Rising (ME04)": "listato",
   "Phantasmal Flames (ME02)": "irraggiungibile",
   "Pokémon 151": "irraggiungibile",
   "Prismatic Evolutions": "irraggiungibile",
   "Crown Zenith": "irraggiungibile",
   "Destined Rivals": "irraggiungibile"
  },
  "PokeCardShop": {
   "Pitch Black (ME05)": "esaurito",
   "30th Celebration": "listato",
   "Storm Emerald (ME06)": "listato",
   "Chaos Rising (ME04)": "esaurito",
   "Phantasmal Flames (ME02)": "esaurito",
   "Pokémon 151": "listato",
   "Prismatic Evolutions": "listato",
   "Crown Zenith": "esaurito",
   "Destined Rivals": "esaurito"
  },
  "Firestorm Games (UK)": {
   "Pitch Black (ME05)": "non listato",
   "30th Celebration": "non listato",
   "Storm Emerald (ME06)": "non listato",
   "Chaos Rising (ME04)": "non listato",
   "Phantasmal Flames (ME02)": "non listato",
   "Pokémon 151": "non listato",
   "Prismatic Evolutions": "non listato",
   "Crown Zenith": "non listato",
   "Destined Rivals": "non listato"
  },
  "Kaissa Games": {
   "Pitch Black (ME05)": "listato",
   "30th Celebration": "non listato",
   "Storm Emerald (ME06)": "non listato",
   "Chaos Rising (ME04)": "listato",
   "Phantasmal Flames (ME02)": "listato",
   "Pokémon 151": "non listato",
   "Prismatic Evolutions": "non listato",
   "Crown Zenith": "non listato",
   "Destined Rivals": "non listato"
  },
  "Deckshop": {
   "Pitch Black (ME05)": "irraggiungibile",
   "30th Celebration": "non listato",
   "Storm Emerald (ME06)": "non listato",
   "Chaos Rising (ME04)": "non listato",
   "Phantasmal Flames (ME02)": "non listato",
   "Pokémon 151": "listato",
   "Prismatic Evolutions": "non listato",
   "Crown Zenith": "non listato",
   "Destined Rivals": "non listato"
  },
  "Card-Corner": {
   "Pitch Black (ME05)": "non listato",
   "30th Celebration": "listato",
   "Storm Emerald (ME06)": "non listato",
   "Chaos Rising (ME04)": "non listato",
   "Phantasmal Flames (ME02)": "non listato",
   "Pokémon 151": "non listato",
   "Prismatic Evolutions": "non listato",
   "Crown Zenith": "non listato",
   "Destined Rivals": "non listato"
  },
  "MistiCards": {
   "Pitch Black (ME05)": "irraggiungibile",
   "30th Celebration": "irraggiungibile",
   "Storm Emerald (ME06)": "irraggiungibile",
   "Chaos Rising (ME04)": "irraggiungibile",
   "Phantasmal Flames (ME02)": "irraggiungibile",
   "Pokémon 151": "irraggiungibile",
   "Prismatic Evolutions": "irraggiungibile",
   "Crown Zenith": "irraggiungibile",
   "Destined Rivals": "irraggiungibile"
  },
  "Pokechest": {
   "Pitch Black (ME05)": "irraggiungibile",
   "30th Celebration": "irraggiungibile",
   "Storm Emerald (ME06)": "irraggiungibile",
   "Chaos Rising (ME04)": "non listato",
   "Phantasmal Flames (ME02)": "non listato",
   "Pokémon 151": "non listato",
   "Prismatic Evolutions": "non listato",
   "Crown Zenith": "non listato",
   "Destined Rivals": "non listato"
  },
  "Fabscards": {
   "Pitch Black (ME05)": "irraggiungibile",
   "30th Celebration": "irraggiungibile",
   "Storm Emerald (ME06)": "irraggiungibile",
   "Chaos Rising (ME04)": "irraggiungibile",
   "Phantasmal Flames (ME02)": "listato",
   "Pokémon 151": "irraggiungibile",
   "Prismatic Evolutions": "irraggiungibile",
   "Crown Zenith": "irraggiungibile",
   "Destined Rivals": "irraggiungibile"
  },
  "TCG-Trade": {
   "Pitch Black (ME05)": "listato",
   "30th Celebration": "listato",
   "Storm Emerald (ME06)": "listato",
   "Chaos Rising (ME04)": "listato",
   "Phantasmal Flames (ME02)": "listato",
   "Pokémon 151": "listato",
   "Prismatic Evolutions": "listato",
   "Crown Zenith": "listato",
   "Destined Rivals": "listato"
  },
  "CardCorner.at": {
   "Pitch Black (ME05)": "irraggiungibile",
   "30th Celebration": "listato",
   "Storm Emerald (ME06)": "irraggiungibile",
   "Chaos Rising (ME04)": "irraggiungibile",
   "Phantasmal Flames (ME02)": "irraggiungibile",
   "Pokémon 151": "irraggiungibile",
   "Prismatic Evolutions": "irraggiungibile",
   "Crown Zenith": "listato",
   "Destined Rivals": "listato"
  },
  "Sapphire-Cards": {
   "Pitch Black (ME05)": "disponibile",
   "30th Celebration": "listato",
   "Storm Emerald (ME06)": "listato",
   "Chaos Rising (ME04)": "disponibile",
   "Phantasmal Flames (ME02)": "disponibile",
   "Pokémon 151": "disponibile",
   "Prismatic Evolutions": "disponibile",
   "Crown Zenith": "disponibile",
   "Destined Rivals": "disponibile"
  },
  "Butticards": {
   "Pitch Black (ME05)": "non listato",
   "30th Celebration": "listato",
   "Storm Emerald (ME06)": "non listato",
   "Chaos Rising (ME04)": "listato",
   "Phantasmal Flames (ME02)": "listato",
   "Pokémon 151": "non listato",
   "Prismatic Evolutions": "non listato",
   "Crown Zenith": "non listato",
   "Destined Rivals": "non listato"
  },
  "RareCards.nl": {
   "Pitch Black (ME05)": "irraggiungibile",
   "30th Celebration": "irraggiungibile",
   "Storm Emerald (ME06)": "irraggiungibile",
   "Chaos Rising (ME04)": "irraggiungibile",
   "Phantasmal Flames (ME02)": "irraggiungibile",
   "Pokémon 151": "irraggiungibile",
   "Prismatic Evolutions": "irraggiungibile",
   "Crown Zenith": "irraggiungibile",
   "Destined Rivals": "irraggiungibile"
  },
  "Pokevend": {
   "Pitch Black (ME05)": "irraggiungibile",
   "30th Celebration": "irraggiungibile",
   "Storm Emerald (ME06)": "irraggiungibile",
   "Chaos Rising (ME04)": "irraggiungibile",
   "Phantasmal Flames (ME02)": "irraggiungibile",
   "Pokémon 151": "irraggiungibile",
   "Prismatic Evolutions": "irraggiungibile",
   "Crown Zenith": "irraggiungibile",
   "Destined Rivals": "irraggiungibile"
  },
  "BESCARDS": {
   "Pitch Black (ME05)": "irraggiungibile",
   "30th Celebration": "irraggiungibile",
   "Storm Emerald (ME06)": "irraggiungibile",
   "Chaos Rising (ME04)": "irraggiungibile",
   "Phantasmal Flames (ME02)": "irraggiungibile",
   "Pokémon 151": "irraggiungibile",
   "Prismatic Evolutions": "irraggiungibile",
   "Crown Zenith": "irraggiungibile",
   "Destined Rivals": "irraggiungibile"
  },
  "Games-Island": {
   "Pitch Black (ME05)": "non listato",
   "30th Celebration": "non listato",
   "Storm Emerald (ME06)": "non listato",
   "Chaos Rising (ME04)": "non listato",
   "Phantasmal Flames (ME02)": "non listato",
   "Pokémon 151": "non listato",
   "Prismatic Evolutions": "non listato",
   "Crown Zenith": "non listato",
   "Destined Rivals": "non listato"
  },
  "Geco-Shop": {
   "Pitch Black (ME05)": "non listato",
   "30th Celebration": "non listato",
   "Storm Emerald (ME06)": "non listato",
   "Chaos Rising (ME04)": "non listato",
   "Phantasmal Flames (ME02)": "non listato",
   "Pokémon 151": "non listato",
   "Prismatic Evolutions": "non listato",
   "Crown Zenith": "non listato",
   "Destined Rivals": "non listato"
  },
  "TCGStore.se": {
   "Pitch Black (ME05)": "irraggiungibile",
   "30th Celebration": "irraggiungibile",
   "Storm Emerald (ME06)": "irraggiungibile",
   "Chaos Rising (ME04)": "irraggiungibile",
   "Phantasmal Flames (ME02)": "irraggiungibile",
   "Pokémon 151": "irraggiungibile",
   "Prismatic Evolutions": "irraggiungibile",
   "Crown Zenith": "irraggiungibile",
   "Destined Rivals": "irraggiungibile"
  },
  "TCGFanshop": {
   "Pitch Black (ME05)": "irraggiungibile",
   "30th Celebration": "irraggiungibile",
   "Storm Emerald (ME06)": "irraggiungibile",
   "Chaos Rising (ME04)": "irraggiungibile",
   "Phantasmal Flames (ME02)": "irraggiungibile",
   "Pokémon 151": "irraggiungibile",
   "Prismatic Evolutions": "irraggiungibile",
   "Crown Zenith": "irraggiungibile",
   "Destined Rivals": "irraggiungibile"
  },
  "Cardmex": {
   "Pitch Black (ME05)": "non listato",
   "30th Celebration": "non listato",
   "Storm Emerald (ME06)": "non listato",
   "Chaos Rising (ME04)": "non listato",
   "Phantasmal Flames (ME02)": "non listato",
   "Pokémon 151": "non listato",
   "Prismatic Evolutions": "non listato",
   "Crown Zenith": "non listato",
   "Destined Rivals": "non listato"
  },
  "Poketalk": {
   "Pitch Black (ME05)": "irraggiungibile",
   "30th Celebration": "irraggiungibile",
   "Storm Emerald (ME06)": "irraggiungibile",
   "Chaos Rising (ME04)": "irraggiungibile",
   "Phantasmal Flames (ME02)": "irraggiungibile",
   "Pokémon 151": "irraggiungibile",
   "Prismatic Evolutions": "irraggiungibile",
   "Crown Zenith": "irraggiungibile",
   "Destined Rivals": "irraggiungibile"
  },
  "Hobbykort": {
   "Pitch Black (ME05)": "irraggiungibile",
   "30th Celebration": "irraggiungibile",
   "Storm Emerald (ME06)": "irraggiungibile",
   "Chaos Rising (ME04)": "irraggiungibile",
   "Phantasmal Flames (ME02)": "irraggiungibile",
   "Pokémon 151": "irraggiungibile",
   "Prismatic Evolutions": "irraggiungibile",
   "Crown Zenith": "listato",
   "Destined Rivals": "listato"
  },
  "PokecTCG": {
   "Pitch Black (ME05)": "listato",
   "30th Celebration": "listato",
   "Storm Emerald (ME06)": "listato",
   "Chaos Rising (ME04)": "listato",
   "Phantasmal Flames (ME02)": "listato",
   "Pokémon 151": "listato",
   "Prismatic Evolutions": "listato",
   "Crown Zenith": "listato",
   "Destined Rivals": "listato"
  },
  "Pokemons.dk": {
   "Pitch Black (ME05)": "listato",
   "30th Celebration": "listato",
   "Storm Emerald (ME06)": "listato",
   "Chaos Rising (ME04)": "listato",
   "Phantasmal Flames (ME02)": "listato",
   "Pokémon 151": "listato",
   "Prismatic Evolutions": "listato",
   "Crown Zenith": "listato",
   "Destined Rivals": "listato"
  },
  "OppaCards": {
   "Pitch Black (ME05)": "listato",
   "30th Celebration": "listato",
   "Storm Emerald (ME06)": "listato",
   "Chaos Rising (ME04)": "listato",
   "Phantasmal Flames (ME02)": "listato",
   "Pokémon 151": "esaurito",
   "Prismatic Evolutions": "listato",
   "Crown Zenith": "listato",
   "Destined Rivals": "listato"
  },
  "Nerdom": {
   "Pitch Black (ME05)": "irraggiungibile",
   "30th Celebration": "irraggiungibile",
   "Storm Emerald (ME06)": "irraggiungibile",
   "Chaos Rising (ME04)": "irraggiungibile",
   "Phantasmal Flames (ME02)": "irraggiungibile",
   "Pokémon 151": "irraggiungibile",
   "Prismatic Evolutions": "irraggiungibile",
   "Crown Zenith": "irraggiungibile",
   "Destined Rivals": "irraggiungibile"
  },
  "WakuWaku": {
   "Pitch Black (ME05)": "irraggiungibile",
   "30th Celebration": "irraggiungibile",
   "Storm Emerald (ME06)": "irraggiungibile",
   "Chaos Rising (ME04)": "irraggiungibile",
   "Phantasmal Flames (ME02)": "irraggiungibile",
   "Pokémon 151": "irraggiungibile",
   "Prismatic Evolutions": "irraggiungibile",
   "Crown Zenith": "irraggiungibile",
   "Destined Rivals": "irraggiungibile"
  },
  "Pokemillon": {
   "Pitch Black (ME05)": "irraggiungibile",
   "30th Celebration": "irraggiungibile",
   "Storm Emerald (ME06)": "irraggiungibile",
   "Chaos Rising (ME04)": "irraggiungibile",
   "Phantasmal Flames (ME02)": "listato",
   "Pokémon 151": "irraggiungibile",
   "Prismatic Evolutions": "irraggiungibile",
   "Crown Zenith": "listato",
   "Destined Rivals": "irraggiungibile"
  },
  "Pokewoke": {
   "Pitch Black (ME05)": "listato",
   "30th Celebration": "listato",
   "Storm Emerald (ME06)": "listato",
   "Chaos Rising (ME04)": "listato",
   "Phantasmal Flames (ME02)": "listato",
   "Pokémon 151": "listato",
   "Prismatic Evolutions": "listato",
   "Crown Zenith": "listato",
   "Destined Rivals": "listato"
  },
  "Pokebank": {
   "Pitch Black (ME05)": "listato",
   "30th Celebration": "listato",
   "Storm Emerald (ME06)": "listato",
   "Chaos Rising (ME04)": "listato",
   "Phantasmal Flames (ME02)": "listato",
   "Pokémon 151": "listato",
   "Prismatic Evolutions": "listato",
   "Crown Zenith": "listato",
   "Destined Rivals": "listato"
  },
  "Pokipair": {
   "Pitch Black (ME05)": "listato",
   "30th Celebration": "listato",
   "Storm Emerald (ME06)": "listato",
   "Chaos Rising (ME04)": "listato",
   "Phantasmal Flames (ME02)": "listato",
   "Pokémon 151": "listato",
   "Prismatic Evolutions": "disponibile",
   "Crown Zenith": "listato",
   "Destined Rivals": "listato"
  },
  "Papelinho": {
   "Pitch Black (ME05)": "irraggiungibile",
   "30th Celebration": "irraggiungibile",
   "Storm Emerald (ME06)": "irraggiungibile",
   "Chaos Rising (ME04)": "irraggiungibile",
   "Phantasmal Flames (ME02)": "irraggiungibile",
   "Pokémon 151": "irraggiungibile",
   "Prismatic Evolutions": "irraggiungibile",
   "Crown Zenith": "irraggiungibile",
   "Destined Rivals": "irraggiungibile"
  },
  "LorenZone": {
   "Pitch Black (ME05)": "irraggiungibile",
   "30th Celebration": "irraggiungibile",
   "Storm Emerald (ME06)": "irraggiungibile",
   "Chaos Rising (ME04)": "irraggiungibile",
   "Phantasmal Flames (ME02)": "irraggiungibile",
   "Pokémon 151": "listato",
   "Prismatic Evolutions": "listato",
   "Crown Zenith": "listato",
   "Destined Rivals": "listato"
  },
  "Vinticards": {
   "Pitch Black (ME05)": "listato",
   "30th Celebration": "listato",
   "Storm Emerald (ME06)": "listato",
   "Chaos Rising (ME04)": "listato",
   "Phantasmal Flames (ME02)": "listato",
   "Pokémon 151": "listato",
   "Prismatic Evolutions": "listato",
   "Crown Zenith": "listato",
   "Destined Rivals": "listato"
  },
  "Pokebox": {
   "Pitch Black (ME05)": "disponibile",
   "30th Celebration": "listato",
   "Storm Emerald (ME06)": "listato",
   "Chaos Rising (ME04)": "listato",
   "Phantasmal Flames (ME02)": "listato",
   "Pokémon 151": "listato",
   "Prismatic Evolutions": "listato",
   "Crown Zenith": "listato",
   "Destined Rivals": "listato"
  },
  "MagicBazar": {
   "Pitch Black (ME05)": "disponibile",
   "30th Celebration": "non listato",
   "Storm Emerald (ME06)": "non listato",
   "Chaos Rising (ME04)": "non listato",
   "Phantasmal Flames (ME02)": "non listato",
   "Pokémon 151": "non listato",
   "Prismatic Evolutions": "non listato",
   "Crown Zenith": "non listato",
   "Destined Rivals": "non listato"
  },
  "TCGDistribution": {
   "Pitch Black (ME05)": "non listato",
   "30th Celebration": "non listato",
   "Storm Emerald (ME06)": "non listato",
   "Chaos Rising (ME04)": "non listato",
   "Phantasmal Flames (ME02)": "non listato",
   "Pokémon 151": "non listato",
   "Prismatic Evolutions": "non listato",
   "Crown Zenith": "non listato",
   "Destined Rivals": "non listato"
  },
  "TCG-Shop.at": {
   "Pitch Black (ME05)": "irraggiungibile",
   "30th Celebration": "irraggiungibile",
   "Storm Emerald (ME06)": "irraggiungibile",
   "Chaos Rising (ME04)": "irraggiungibile",
   "Phantasmal Flames (ME02)": "irraggiungibile",
   "Pokémon 151": "irraggiungibile",
   "Prismatic Evolutions": "irraggiungibile",
   "Crown Zenith": "irraggiungibile",
   "Destined Rivals": "irraggiungibile"
  },
  "Fuji-Store": {
   "Pitch Black (ME05)": "listato",
   "30th Celebration": "listato",
   "Storm Emerald (ME06)": "listato",
   "Chaos Rising (ME04)": "listato",
   "Phantasmal Flames (ME02)": "listato",
   "Pokémon 151": "listato",
   "Prismatic Evolutions": "listato",
   "Crown Zenith": "listato",
   "Destined Rivals": "listato"
  },
  "Pikashop": {
   "Pitch Black (ME05)": "listato",
   "30th Celebration": "listato",
   "Storm Emerald (ME06)": "listato",
   "Chaos Rising (ME04)": "disponibile",
   "Phantasmal Flames (ME02)": "esaurito",
   "Pokémon 151": "listato",
   "Prismatic Evolutions": "listato",
   "Crown Zenith": "listato",
   "Destined Rivals": "listato"
  },
  "Pokeka.hu": {
   "Pitch Black (ME05)": "irraggiungibile",
   "30th Celebration": "irraggiungibile",
   "Storm Emerald (ME06)": "irraggiungibile",
   "Chaos Rising (ME04)": "irraggiungibile",
   "Phantasmal Flames (ME02)": "non listato",
   "Pokémon 151": "irraggiungibile",
   "Prismatic Evolutions": "non listato",
   "Crown Zenith": "irraggiungibile",
   "Destined Rivals": "irraggiungibile"
  },
  "LetsGoTry": {
   "Pitch Black (ME05)": "listato",
   "30th Celebration": "non listato",
   "Storm Emerald (ME06)": "non listato",
   "Chaos Rising (ME04)": "listato",
   "Phantasmal Flames (ME02)": "non listato",
   "Pokémon 151": "non listato",
   "Prismatic Evolutions": "non listato",
   "Crown Zenith": "non listato",
   "Destined Rivals": "non listato"
  },
  "Pokekarty": {
   "Pitch Black (ME05)": "listato",
   "30th Celebration": "listato",
   "Storm Emerald (ME06)": "listato",
   "Chaos Rising (ME04)": "disponibile",
   "Phantasmal Flames (ME02)": "disponibile",
   "Pokémon 151": "listato",
   "Prismatic Evolutions": "listato",
   "Crown Zenith": "disponibile",
   "Destined Rivals": "disponibile"
  },
  "TCGPikas": {
   "Pitch Black (ME05)": "non listato",
   "30th Celebration": "non listato",
   "Storm Emerald (ME06)": "non listato",
   "Chaos Rising (ME04)": "listato",
   "Phantasmal Flames (ME02)": "listato",
   "Pokémon 151": "non listato",
   "Prismatic Evolutions": "listato",
   "Crown Zenith": "non listato",
   "Destined Rivals": "listato"
  },
  "PokemonWorld.lt": {
   "Pitch Black (ME05)": "non listato",
   "30th Celebration": "non listato",
   "Storm Emerald (ME06)": "non listato",
   "Chaos Rising (ME04)": "non listato",
   "Phantasmal Flames (ME02)": "non listato",
   "Pokémon 151": "listato",
   "Prismatic Evolutions": "listato",
   "Crown Zenith": "listato",
   "Destined Rivals": "listato"
  },
  "Pokemonia.ro": {
   "Pitch Black (ME05)": "irraggiungibile",
   "30th Celebration": "irraggiungibile",
   "Storm Emerald (ME06)": "irraggiungibile",
   "Chaos Rising (ME04)": "irraggiungibile",
   "Phantasmal Flames (ME02)": "irraggiungibile",
   "Pokémon 151": "irraggiungibile",
   "Prismatic Evolutions": "irraggiungibile",
   "Crown Zenith": "irraggiungibile",
   "Destined Rivals": "irraggiungibile"
  },
  "Pokemania.ro": {
   "Pitch Black (ME05)": "disponibile",
   "30th Celebration": "non listato",
   "Storm Emerald (ME06)": "non listato",
   "Chaos Rising (ME04)": "listato",
   "Phantasmal Flames (ME02)": "listato",
   "Pokémon 151": "listato",
   "Prismatic Evolutions": "listato",
   "Crown Zenith": "listato",
   "Destined Rivals": "listato"
  },
  "PokeBros": {
   "Pitch Black (ME05)": "non listato",
   "30th Celebration": "non listato",
   "Storm Emerald (ME06)": "non listato",
   "Chaos Rising (ME04)": "listato",
   "Phantasmal Flames (ME02)": "non listato",
   "Pokémon 151": "non listato",
   "Prismatic Evolutions": "non listato",
   "Crown Zenith": "non listato",
   "Destined Rivals": "non listato"
  },
  "iTCG.bg": {
   "Pitch Black (ME05)": "irraggiungibile",
   "30th Celebration": "irraggiungibile",
   "Storm Emerald (ME06)": "non listato",
   "Chaos Rising (ME04)": "non listato",
   "Phantasmal Flames (ME02)": "non listato",
   "Pokémon 151": "non listato",
   "Prismatic Evolutions": "non listato",
   "Crown Zenith": "non listato",
   "Destined Rivals": "irraggiungibile"
  },
  "Stoyanov Games": {
   "Pitch Black (ME05)": "non listato",
   "30th Celebration": "non listato",
   "Storm Emerald (ME06)": "non listato",
   "Chaos Rising (ME04)": "non listato",
   "Phantasmal Flames (ME02)": "non listato",
   "Pokémon 151": "non listato",
   "Prismatic Evolutions": "non listato",
   "Crown Zenith": "non listato",
   "Destined Rivals": "non listato"
  },
  "Pokecollect": {
   "Pitch Black (ME05)": "disponibile",
   "30th Celebration": "non listato",
   "Storm Emerald (ME06)": "non listato",
   "Chaos Rising (ME04)": "disponibile",
   "Phantasmal Flames (ME02)": "non listato",
   "Pokémon 151": "non listato",
   "Prismatic Evolutions": "listato",
   "Crown Zenith": "listato",
   "Destined Rivals": "non listato"
  },
  "LottiCards": {
   "Pitch Black (ME05)": "non listato",
   "30th Celebration": "non listato",
   "Storm Emerald (ME06)": "non listato",
   "Chaos Rising (ME04)": "non listato",
   "Phantasmal Flames (ME02)": "non listato",
   "Pokémon 151": "non listato",
   "Prismatic Evolutions": "non listato",
   "Crown Zenith": "non listato",
   "Destined Rivals": "non listato"
  },
  "TCG Company": {
   "Pitch Black (ME05)": "irraggiungibile",
   "30th Celebration": "irraggiungibile",
   "Storm Emerald (ME06)": "irraggiungibile",
   "Chaos Rising (ME04)": "irraggiungibile",
   "Phantasmal Flames (ME02)": "irraggiungibile",
   "Pokémon 151": "irraggiungibile",
   "Prismatic Evolutions": "irraggiungibile",
   "Crown Zenith": "irraggiungibile",
   "Destined Rivals": "irraggiungibile"
  },
  "ExtremePokeCorner": {
   "Pitch Black (ME05)": "listato",
   "30th Celebration": "listato",
   "Storm Emerald (ME06)": "listato",
   "Chaos Rising (ME04)": "listato",
   "Phantasmal Flames (ME02)": "listato",
   "Pokémon 151": "listato",
   "Prismatic Evolutions": "listato",
   "Crown Zenith": "listato",
   "Destined Rivals": "listato"
  },
  "GameLife (IT)": {
   "Pitch Black (ME05)": "irraggiungibile",
   "30th Celebration": "irraggiungibile",
   "Storm Emerald (ME06)": "irraggiungibile",
   "Chaos Rising (ME04)": "irraggiungibile",
   "Phantasmal Flames (ME02)": "irraggiungibile",
   "Pokémon 151": "irraggiungibile",
   "Prismatic Evolutions": "irraggiungibile",
   "Crown Zenith": "irraggiungibile",
   "Destined Rivals": "irraggiungibile"
  },
  "GameStop Italia": {
   "Pitch Black (ME05)": "irraggiungibile",
   "30th Celebration": "irraggiungibile",
   "Storm Emerald (ME06)": "irraggiungibile",
   "Chaos Rising (ME04)": "irraggiungibile",
   "Phantasmal Flames (ME02)": "irraggiungibile",
   "Pokémon 151": "irraggiungibile",
   "Prismatic Evolutions": "irraggiungibile",
   "Crown Zenith": "irraggiungibile",
   "Destined Rivals": "irraggiungibile"
  }
 },
 "search_url": {
  "eurotcg.com": "https://eurotcg.com/search?q={q}",
  "www.efantasy.gr": "https://www.efantasy.gr/search?q={q}",
  "rogerz.dk": "https://rogerz.dk/search?q={q}",
  "poke-power.eu": "https://poke-power.eu/search?q={q}",
  "sunnystore.es": "https://sunnystore.es/search?q={q}",
  "kaissagames.com": "https://kaissagames.com/search?q={q}",
  "www.pokecardshop.be": "https://www.pokecardshop.be/search?q={q}",
  "www.chaoscards.co.uk": "https://www.chaoscards.co.uk/search?q={q}",
  "packratt.co.uk": "https://packratt.co.uk/search?q={q}",
  "totalcards.net": "https://totalcards.net/search?controller=search&s={q}",
  "www.firestormgames.co.uk": "https://www.firestormgames.co.uk/?s={q}&post_type=product",
  "www.card-corner.de": "https://www.card-corner.de/search?q={q}",
  "pokebros.com.hr": "https://pokebros.com.hr/search?q={q}",
  "sapphire-cards.de": "https://sapphire-cards.de/?s={q}&post_type=product",
  "tcg-trade.de": "https://tcg-trade.de/search?q={q}",
  "www.butticards.at": "https://www.butticards.at/?s={q}&post_type=product",
  "games-island.eu": "https://games-island.eu/search?q={q}",
  "cardmex-shop.de": "https://cardmex-shop.de/?s={q}&post_type=product",
  "geco-shop.de": "https://geco-shop.de/search?q={q}",
  "oppacards.com": "https://oppacards.com/?s={q}&post_type=product",
  "www.cardstore.cz": "https://www.cardstore.cz/?s={q}&post_type=product",
  "www.pokipair.com": "https://www.pokipair.com/?s={q}&post_type=product",
  "vinticards.com": "https://vinticards.com/search?q={q}",
  "pokeboxstore.pt": "https://pokeboxstore.pt/?s={q}&post_type=product",
  "www.magicbazar.fr": "https://www.magicbazar.fr/?s={q}&post_type=product",
  "fuji-store.fr": "https://fuji-store.fr/?s={q}&post_type=product",
  "tcgdistribution.fr": "https://tcgdistribution.fr/?s={q}&post_type=product",
  "www.pokekarty.pl": "https://www.pokekarty.pl/?s={q}&post_type=product",
  "letsgotry.pl": "https://letsgotry.pl/?s={q}&post_type=product",
  "pokecollect.pl": "https://pokecollect.pl/?s={q}&post_type=product",
  "pokemania.ro": "https://pokemania.ro/?s={q}&post_type=product",
  "stoyanov-gamesbg.com": "https://stoyanov-gamesbg.com/search?q={q}",
  "www.lotticards.de": "https://www.lotticards.de/search?q={q}",
  "tradingcard.fi": "https://tradingcard.fi/?s={q}&post_type=product",
  "bescards.com": "https://bescards.com/search?q={q}",
  "www.pokemons.dk": "https://www.pokemons.dk/?s={q}&post_type=product",
  "pokectcg.cz": "https://pokectcg.cz/?s={q}&post_type=product",
  "pokewoke.store": "https://pokewoke.store/?s={q}&post_type=product",
  "extremepokecorner.com": "https://extremepokecorner.com/?s={q}&post_type=product",
  "pikashop.pl": "https://pikashop.pl/?s={q}&post_type=product",
  "tcgpikas.lt": "https://tcgpikas.lt/?s={q}&post_type=product",
  "pokemonworld.lt": "https://pokemonworld.lt/?s={q}&post_type=product",
  "cardzone.es": "https://cardzone.es/search?q={q}",
  "outpostbrussels.be": "https://outpostbrussels.be/search?q={q}",
  "alldaytcg.com": "https://alldaytcg.com/search?q={q}",
  "godofcards.com": "https://godofcards.com/search?q={q}",
  "www.pokemillon.com": "https://www.pokemillon.com/?s={q}&post_type=product",
  "pokebank.es": "https://pokebank.es/?s={q}&post_type=product",
  "www.blackfire.eu": "https://www.blackfire.eu/search?q={q}",
  "hobbykort.se": "https://hobbykort.se/search?q={q}",
  "pokechest.at": "https://pokechest.at/search?controller=search&s={q}",
  "cardcorner.at": "https://cardcorner.at/search?q={q}",
  "itcg.bg": "https://itcg.bg/?s={q}&post_type=product",
  "crispycards.de": "https://crispycards.de/search?q={q}",
  "tcgstore.se": "https://tcgstore.se/?s={q}&post_type=product",
  "pokeka.hu": "https://pokeka.hu/search?controller=search&s={q}",
  "www.deckshop.de": "https://www.deckshop.de/search?controller=search&s={q}",
  "fabscards.at": "https://fabscards.at/search?q={q}",
  "rarecards.nl": "https://rarecards.nl/?s={q}&post_type=product",
  "www.poketalk.se": "https://www.poketalk.se/?s={q}&post_type=product",
  "lorenzone.fr": "https://lorenzone.fr/search?q={q}"
 },
 "alerts": {
  "Cardstore.cz|30th Celebration": 1783014113.9441674,
  "Sapphire-Cards|Pitch Black (ME05)": 1783017425.191381,
  "drop|MagicBazar|Pitch Black (ME05)": 1783047065.5997376,
  "LetsGoTry|30th Celebration": 1783046156.5635478,
  "Amazon.it|Prismatic Evolutions": 1783045533.536075,
  "Amazon.it|Crown Zenith": 1783045533.536075,
  "Amazon.it|Destined Rivals": 1783044060.0334783,
  "CardZone|30th Celebration": 1783044643.570895,
  "CardZone|Chaos Rising (ME04)": 1783042842.9346313,
  "Amazon.it|30th Celebration": 1783021246.4570694,
  "Amazon.it|Storm Emerald (ME06)": 1783021246.4570694,
  "Amazon.it|Chaos Rising (ME04)": 1783045533.536075,
  "Amazon.it|Phantasmal Flames (ME02)": 1783044642.043092,
  "Amazon.it|Pokémon 151": 1783045533.536075,
  "PokeCardShop|Pitch Black (ME05)": 1783021262.714947,
  "Amazon.it|Pitch Black (ME05)": 1783043441.3616652,
  "CardZone|Pitch Black (ME05)": 1783046127.4060724,
  "CardZone|Storm Emerald (ME06)": 1783046444.6166468,
  "PokeCardShop|Chaos Rising (ME04)": 1783027262.2730978,
  "MagicBazar|Prismatic Evolutions": 1783027887.2810962,
  "PokeCardShop|Phantasmal Flames (ME02)": 1783028458.9307673,
  "CardZone|Phantasmal Flames (ME02)": 1783054864.5105546,
  "PokeCardShop|30th Celebration": 1783049147.3515093
 },
 "prices": {
  "SunnyStore|Pokémon 151": "€26,90",
  "Packratt (UK)|Chaos Rising (ME04)": "£10.01",
  "Packratt (UK)|Pokémon 151": "£29.99",
  "MagicBazar|Pitch Black (ME05)": "$85"
 },
 "urls": {
  "SunnyStore|Pokémon 151": "https://sunnystore.es/search?q=pokemon+151",
  "Packratt (UK)|Chaos Rising (ME04)": "https://packratt.co.uk/search?q=chaos+rising",
  "Packratt (UK)|Pokémon 151": "https://packratt.co.uk/search?q=pokemon+151",
  "Sapphire-Cards|Chaos Rising (ME04)": "https://sapphire-cards.de/?s=chaos+rising&post_type=product",
  "Sapphire-Cards|Phantasmal Flames (ME02)": "https://sapphire-cards.de/?s=phantasmal+flames&post_type=product",
  "Sapphire-Cards|Pokémon 151": "https://sapphire-cards.de/?s=pokemon+151&post_type=product",
  "Sapphire-Cards|Prismatic Evolutions": "https://sapphire-cards.de/?s=prismatic+evolutions&post_type=product",
  "Sapphire-Cards|Crown Zenith": "https://sapphire-cards.de/?s=crown+zenith&post_type=product",
  "Sapphire-Cards|Destined Rivals": "https://sapphire-cards.de/?s=destined+rivals&post_type=product",
  "Pokipair|Prismatic Evolutions": "https://www.pokipair.com/?s=prismatic+evolutions&post_type=product",
  "Pokebox|Pitch Black (ME05)": "https://pokeboxstore.pt/produto/premium-checklane-blister-gengar-pitch-black/",
  "MagicBazar|Pitch Black (ME05)": "https://www.magicbazar.fr/en/produit/647162/gift-bundle-marvel-super-heroes-magic-en",
  "Pokekarty|Chaos Rising (ME04)": "https://www.pokekarty.pl/product/karta-pokemon-chaos-rising-003-086-beedrill-ex",
  "Pokekarty|Phantasmal Flames (ME02)": "https://www.pokekarty.pl/product/karta-pokemon-phantasmal-flames-004-094-mega-heracross-ex",
  "Pokekarty|Crown Zenith": "https://www.pokekarty.pl/product/karta-pokemon-crown-zenith-046-159-rotom-vstar",
  "Pokekarty|Destined Rivals": "https://www.pokekarty.pl/product/pokemon-tcg-destined-rivals-booster",
  "Pikashop|Chaos Rising (ME04)": "https://pikashop.pl/?s=chaos+rising&post_type=product",
  "Pokemania.ro|Pitch Black (ME05)": "https://pokemania.ro/vstar-universe/pokemon-tcg-vstar-universes-s12a-jp-booster-bundle-display-box-10-pachete-booster-jp",
  "Pokecollect|Pitch Black (ME05)": "https://pokecollect.pl/?s=pitch+black&post_type=product",
  "Pokecollect|Chaos Rising (ME04)": "https://pokecollect.pl/?s=chaos+rising&post_type=product",
  "CardZone|Pitch Black (ME05)": "https://cardzone.es/search?q=pitch+black",
  "Sapphire-Cards|Pitch Black (ME05)": "https://sapphire-cards.de/?s=pitch+black&post_type=product",
  "CardZone|30th Celebration": "https://cardzone.es/search?q=30th+celebration",
  "CardZone|Chaos Rising (ME04)": "https://cardzone.es/search?q=chaos+rising",
  "PokeCardShop|Pitch Black (ME05)": "https://www.pokecardshop.be/product-page/pokémon-pitch-black-booster-box",
  "CardZone|Storm Emerald (ME06)": "https://cardzone.es/search?q=storm+emerald",
  "PokeCardShop|Chaos Rising (ME04)": "https://www.pokecardshop.be/search?q=chaos+rising",
  "PokeCardShop|Phantasmal Flames (ME02)": "https://www.pokecardshop.be/search?q=phantasmal+flames",
  "God of Cards|Pokémon 151": "https://godofcards.com/search?q=pokemon+151",
  "CardZone|Phantasmal Flames (ME02)": "https://cardzone.es/search?q=phantasmal+flames",
  "CardZone|Crown Zenith": "https://cardzone.es/search?q=crown+zenith",
  "God of Cards|Prismatic Evolutions": "https://godofcards.com/search?q=prismatic+evolutions"
 },
 "log": [
  {
   "ts": "02/07 21:35",
   "title": "🚨 30th Celebration — CardZone",
   "url": "https://cardzone.es/search?q=30th+celebration"
  },
  {
   "ts": "02/07 21:40",
   "title": "🚨 Chaos Rising (ME04) — CardZone",
   "url": "https://cardzone.es/search?q=chaos+rising"
  },
  {
   "ts": "02/07 21:40",
   "title": "🚨 30th Celebration — Amazon.it",
   "url": "https://www.amazon.it/s?k=pokemon+tcg+30th+celebration"
  },
  {
   "ts": "02/07 21:40",
   "title": "🚨 Storm Emerald (ME06) — Amazon.it",
   "url": "https://www.amazon.it/s?k=pokemon+tcg+storm+emerald"
  },
  {
   "ts": "02/07 21:40",
   "title": "🚨 Chaos Rising (ME04) — Amazon.it",
   "url": "https://www.amazon.it/s?k=pokemon+tcg+chaos+rising"
  },
  {
   "ts": "02/07 21:40",
   "title": "🚨 Phantasmal Flames (ME02) — Amazon.it",
   "url": "https://www.amazon.it/s?k=pokemon+tcg+phantasmal+flames"
  },
  {
   "ts": "02/07 21:40",
   "title": "🚨 Pokémon 151 — Amazon.it",
   "url": "https://www.amazon.it/s?k=pokemon+tcg+pokemon+151"
  },
  {
   "ts": "02/07 21:41",
   "title": "🚨 Pitch Black (ME05) — PokeCardShop",
   "url": "https://www.pokecardshop.be/product-page/pokémon-pitch-black-booster-box"
  },
  {
   "ts": "02/07 21:45",
   "title": "🚨 Pitch Black (ME05) — Amazon.it",
   "url": "https://www.amazon.it/s?k=pokemon+tcg+pitch+black"
  },
  {
   "ts": "02/07 22:14",
   "title": "🚨 Pitch Black (ME05) — CardZone",
   "url": "https://cardzone.es/search?q=pitch+black"
  },
  {
   "ts": "02/07 22:32",
   "title": "🚨 Storm Emerald (ME06) — CardZone",
   "url": "https://cardzone.es/search?q=storm+emerald"
  },
  {
   "ts": "02/07 23:21",
   "title": "🚨 Chaos Rising (ME04) — PokeCardShop",
   "url": "https://www.pokecardshop.be/search?q=chaos+rising"
  },
  {
   "ts": "02/07 23:31",
   "title": "🚨 Prismatic Evolutions — MagicBazar",
   "url": "https://www.magicbazar.fr/?s=prismatic+evolutions&post_type=product"
  },
  {
   "ts": "02/07 23:40",
   "title": "🚨 Phantasmal Flames (ME02) — PokeCardShop",
   "url": "https://www.pokecardshop.be/search?q=phantasmal+flames"
  },
  {
   "ts": "03/07 00:55",
   "title": "🚨 Phantasmal Flames (ME02) — CardZone",
   "url": "https://cardzone.es/search?q=phantasmal+flames"
  },
  {
   "ts": "03/07 03:40",
   "title": "🚨 Chaos Rising (ME04) — CardZone",
   "url": "https://cardzone.es/search?q=chaos+rising"
  },
  {
   "ts": "03/07 03:50",
   "title": "🚨 Pitch Black (ME05) — Amazon.it",
   "url": "https://www.amazon.it/s?k=pokemon+tcg+pitch+black"
  },
  {
   "ts": "03/07 04:01",
   "title": "🚨 Destined Rivals — Amazon.it",
   "url": "https://www.amazon.it/s?k=pokemon+tcg+destined+rivals"
  },
  {
   "ts": "03/07 04:10",
   "title": "🚨 Phantasmal Flames (ME02) — Amazon.it",
   "url": "https://www.amazon.it/s?k=pokemon+tcg+phantasmal+flames"
  },
  {
   "ts": "03/07 04:10",
   "title": "🚨 30th Celebration — CardZone",
   "url": "https://cardzone.es/search?q=30th+celebration"
  },
  {
   "ts": "03/07 04:25",
   "title": "🚨 Chaos Rising (ME04) — Amazon.it",
   "url": "https://www.amazon.it/s?k=pokemon+tcg+chaos+rising"
  },
  {
   "ts": "03/07 04:25",
   "title": "🚨 Pokémon 151 — Amazon.it",
   "url": "https://www.amazon.it/s?k=pokemon+tcg+pokemon+151"
  },
  {
   "ts": "03/07 04:25",
   "title": "🚨 Prismatic Evolutions — Amazon.it",
   "url": "https://www.amazon.it/s?k=pokemon+tcg+prismatic+evolutions"
  },
  {
   "ts": "03/07 04:25",
   "title": "🚨 Crown Zenith — Amazon.it",
   "url": "https://www.amazon.it/s?k=pokemon+tcg+crown+zenith"
  },
  {
   "ts": "03/07 04:35",
   "title": "🚨 Pitch Black (ME05) — CardZone",
   "url": "https://cardzone.es/search?q=pitch+black"
  },
  {
   "ts": "03/07 04:35",
   "title": "🚨 30th Celebration — LetsGoTry",
   "url": "https://letsgotry.pl/?s=30th+celebration&post_type=product"
  },
  {
   "ts": "03/07 04:40",
   "title": "🚨 Storm Emerald (ME06) — CardZone",
   "url": "https://cardzone.es/search?q=storm+emerald"
  },
  {
   "ts": "03/07 04:51",
   "title": "📉 Prezzo giù: Pitch Black (ME05) — MagicBazar",
   "url": "https://www.magicbazar.fr/en/produit/647162/gift-bundle-marvel-super-heroes-magic-en"
  },
  {
   "ts": "03/07 05:25",
   "title": "🚨 30th Celebration — PokeCardShop",
   "url": "https://www.pokecardshop.be/search?q=30th+celebration"
  },
  {
   "ts": "03/07 07:01",
   "title": "🚨 Phantasmal Flames (ME02) — CardZone",
   "url": "https://cardzone.es/search?q=phantasmal+flames"
  }
 ],
 "digest_slot": "2026-07-02-22"
}